tests/__init__.py
tests/tf_keras_vis/__init__.py
tests/tf_keras_vis/attentions_test.py
tests/tf_keras_vis/conftest.py
tests/tf_keras_vis/gradcam_plus_plus_test.py
tests/tf_keras_vis/gradcam_test.py
tests/tf_keras_vis/saliency_test.py
tests/tf_keras_vis/scorecam_test.py
tests/tf_keras_vis/tf_keras_vis_test.py
tests/tf_keras_vis/activation_maximization/__init__.py
tests/tf_keras_vis/activation_maximization/activation_maximization_test.py
tests/tf_keras_vis/activation_maximization/callbacks_test.py
tests/tf_keras_vis/activation_maximization/input_modifiers_test.py
tests/tf_keras_vis/utils/__init__.py
tests/tf_keras_vis/utils/model_modifiers_test.py
tests/tf_keras_vis/utils/scores_test.py
tests/tf_keras_vis/utils/utils_test.py
tf_keras_vis/__init__.py
tf_keras_vis/gradcam.py
tf_keras_vis/gradcam_plus_plus.py
tf_keras_vis/layercam.py
tf_keras_vis/saliency.py
tf_keras_vis/scorecam.py
tf_keras_vis/activation_maximization/__init__.py
tf_keras_vis/activation_maximization/callbacks.py
tf_keras_vis/activation_maximization/input_modifiers.py
tf_keras_vis/activation_maximization/regularizers.py
tf_keras_vis/utils/__init__.py
tf_keras_vis/utils/callbacks.py
tf_keras_vis/utils/input_modifiers.py
tf_keras_vis/utils/losses.py
tf_keras_vis/utils/model_modifiers.py
tf_keras_vis/utils/regularizers.py
tf_keras_vis/utils/scores.py
tf_keras_vis/utils/test.py
tf_keras_vis-0.8.7.dist-info/LICENSE
tf_keras_vis-0.8.7.dist-info/METADATA
tf_keras_vis-0.8.7.dist-info/WHEEL
tf_keras_vis-0.8.7.dist-info/top_level.txt
tf_keras_vis-0.8.7.dist-info/RECORD
