Metadata-Version: 2.1
Name: tf-keras-vis
Version: 0.8.7
Summary: Neural network visualization toolkit for tf.keras
Home-page: https://github.com/keisen/tf-keras-vis
Author: keisen (Yasuhiro Kubota)
Author-email: k.keisen@gmail.com
Classifier: Intended Audience :: Developers
Classifier: Intended Audience :: Education
Classifier: Intended Audience :: Science/Research
Classifier: License :: OSI Approved :: MIT License
Classifier: Operating System :: OS Independent
Classifier: Programming Language :: Python :: 3
Classifier: Programming Language :: Python :: 3 :: Only
Classifier: Programming Language :: Python :: 3.7
Classifier: Programming Language :: Python :: 3.8
Classifier: Programming Language :: Python :: 3.9
Classifier: Programming Language :: Python :: 3.10
Classifier: Programming Language :: Python :: 3.11
Classifier: Programming Language :: Python :: 3.12
Classifier: Topic :: Education
Classifier: Topic :: Scientific/Engineering
Classifier: Topic :: Scientific/Engineering :: Artificial Intelligence
Classifier: Topic :: Scientific/Engineering :: Image Recognition
Classifier: Topic :: Scientific/Engineering :: Visualization
Classifier: Topic :: Software Development
Classifier: Topic :: Software Development :: Libraries
Classifier: Topic :: Software Development :: Libraries :: Python Modules
Requires-Python: >=3.7
License-File: LICENSE
Requires-Dist: scipy
Requires-Dist: pillow
Requires-Dist: deprecated
Requires-Dist: imageio
Requires-Dist: packaging
Requires-Dist: importlib-metadata ; python_version < "3.8"
Provides-Extra: develop
Requires-Dist: flake8 ; extra == 'develop'
Requires-Dist: flake8-docstrings ; extra == 'develop'
Requires-Dist: isort ; extra == 'develop'
Requires-Dist: yapf ; extra == 'develop'
Requires-Dist: pytest ; extra == 'develop'
Requires-Dist: pytest-pycodestyle ; extra == 'develop'
Requires-Dist: pytest-cov ; extra == 'develop'
Requires-Dist: pytest-env ; extra == 'develop'
Requires-Dist: pytest-xdist ; extra == 'develop'
Provides-Extra: docs
Requires-Dist: sphinx ; extra == 'docs'
Requires-Dist: sphinx-autobuild ; extra == 'docs'
Requires-Dist: sphinx-rtd-theme ; extra == 'docs'
Requires-Dist: myst-parser ; extra == 'docs'
Requires-Dist: nbsphinx ; extra == 'docs'
Requires-Dist: pandoc ; extra == 'docs'
Provides-Extra: examples
Requires-Dist: jupyterlab ; extra == 'examples'
Requires-Dist: matplotlib ; extra == 'examples'
